ocr_app.py
ocr_image.py
run_ocr_app.py
texify/inference.py
texify/model/config.py
texify/model/model.py
texify/model/processor.py
texify/output.py
texify/settings.py
texify/util.py
texify-0.2.1.dist-info/LICENSE
texify-0.2.1.dist-info/METADATA
texify-0.2.1.dist-info/WHEEL
texify-0.2.1.dist-info/entry_points.txt
texify-0.2.1.dist-info/RECORD
