Metadata-Version: 2.1
Name: texify
Version: 0.2.1
Summary: OCR for latex images
Home-page: https://github.com/VikParuchuri/texify
License: GPL-3.0-or-later
Keywords: ocr,latex,markdown,pdf
Author: Vik Paruchuri
Author-email: vik.paruchuri@gmail.com
Requires-Python: >=3.10,<4.0
Classifier: License :: OSI Approved :: GNU General Public License v3 or later (GPLv3+)
Classifier: Programming Language :: Python :: 3
Classifier: Programming Language :: Python :: 3.10
Classifier: Programming Language :: Python :: 3.11
Classifier: Programming Language :: Python :: 3.12
Classifier: Programming Language :: Python :: 3.13
Requires-Dist: Pillow (>=10.1.0,<11.0.0)
Requires-Dist: ftfy (>=6.1.3,<7.0.0)
Requires-Dist: pydantic (>=2.5.2,<3.0.0)
Requires-Dist: pydantic-settings (>=2.1.0,<3.0.0)
Requires-Dist: pypdfium2 (>=4.25.0,<5.0.0)
Requires-Dist: python-dotenv (>=1.0.0,<2.0.0)
Requires-Dist: torch (>=2.1.2,<3.0.0)
Requires-Dist: transformers (>=4.36.2,<5.0.0)
Project-URL: Repository, https://github.com/VikParuchuri/texify
